evolly/__init__.py
evolly/analyze_runs.py
evolly/evolution.py
evolly/model_builder.py
evolly/utils.py
evolly/visualize_run.py
evolly/blocks/__init__.py
evolly/blocks/tensorflow/__init__.py
evolly/blocks/tensorflow/inception_resnet_v2_se.py
evolly/blocks/tensorflow/initializers.py
evolly/blocks/tensorflow/misc.py
evolly/blocks/tensorflow/mobilenet.py
evolly/blocks/tensorflow/pose.py
evolly/blocks/tensorflow/regularizers.py
evolly/blocks/tensorflow/resnet.py
evolly/blocks/torch/__init__.py
evolly/blocks/torch/conv2d_same.py
evolly/blocks/torch/inception_resnet_v2_se.py
evolly/blocks/torch/misc.py
evolly/blocks/torch/mobilenet.py
evolly/blocks/torch/padding.py
evolly/blocks/torch/resnet.py
evolly-0.1.0.dist-info/LICENSE
evolly-0.1.0.dist-info/METADATA
evolly-0.1.0.dist-info/WHEEL
evolly-0.1.0.dist-info/top_level.txt
evolly-0.1.0.dist-info/RECORD
