Metadata-Version: 2.1
Name: evolly
Version: 0.1.0
Summary: Evolutionary NAS framework
Home-page: https://github.com/revisorteam/evolly
Author: The Revisor Team
Author-email: revisorteam@pm.me
License: MIT
Platform: UNKNOWN
Classifier: Development Status :: 5 - Production/Stable
Classifier: Environment :: Console
Classifier: License :: OSI Approved :: MIT License
Classifier: Intended Audience :: Science/Research
Classifier: Programming Language :: Python :: 3
Classifier: Topic :: Scientific/Engineering :: Artificial Intelligence
License-File: LICENSE
Requires-Dist: yacs
Requires-Dist: numpy
Requires-Dist: pandas
Requires-Dist: matplotlib
Requires-Dist: tabulate
Requires-Dist: diagrams
Requires-Dist: fvcore
Requires-Dist: opencv-python
Provides-Extra: tensorflow
Requires-Dist: tensorflow (>=2.3) ; extra == 'tensorflow'
Provides-Extra: tensorflow-cpu
Requires-Dist: tensorflow-cpu (>=2.3) ; extra == 'tensorflow-cpu'
Provides-Extra: tensorflow-gpu
Requires-Dist: tensorflow-gpu (>=2.3) ; extra == 'tensorflow-gpu'
Provides-Extra: torch
Requires-Dist: torch (>=1.9.0) ; extra == 'torch'
Provides-Extra: torchvision
Requires-Dist: torchvision (>=0.10.0) ; extra == 'torchvision'
